nxsrecconfig/CheckerThread.py
nxsrecconfig/Converter.py
nxsrecconfig/Describer.py
nxsrecconfig/DynamicComponent.py
nxsrecconfig/MacroServerPools.py
nxsrecconfig/NXSConfig.py
nxsrecconfig/ProfileManager.py
nxsrecconfig/Release.py
nxsrecconfig/Selection.py
nxsrecconfig/Selector.py
nxsrecconfig/Settings.py
nxsrecconfig/StreamSet.py
nxsrecconfig/Utils.py
nxsrecconfig/__init__.py
nxsrecselector-4.3.0.data/scripts/NXSRecSelector
nxsrecselector-4.3.0.dist-info/METADATA
nxsrecselector-4.3.0.dist-info/WHEEL
nxsrecselector-4.3.0.dist-info/top_level.txt
nxsrecselector-4.3.0.dist-info/RECORD
